trento_agent_sdk/__init__.py
trento_agent_sdk/a2a_client.py
trento_agent_sdk/a2a_server.py
trento_agent_sdk/logging_config.py
trento_agent_sdk/a2a/TaskManager.py
trento_agent_sdk/a2a/__init__.py
trento_agent_sdk/a2a/models/AgentCard.py
trento_agent_sdk/a2a/models/Task.py
trento_agent_sdk/a2a/models/Types.py
trento_agent_sdk/a2a/models/__init__.py
trento_agent_sdk/agent/__init__.py
trento_agent_sdk/agent/agent.py
trento_agent_sdk/agent/agent_manager.py
trento_agent_sdk/agent/models.py
trento_agent_sdk/agent/utils.py
trento_agent_sdk/memory/__init__.py
trento_agent_sdk/memory/memory.py
trento_agent_sdk/tool/__init__.py
trento_agent_sdk/tool/func_metadata.py
trento_agent_sdk/tool/tool.py
trento_agent_sdk/tool/tool_manager.py
trento_agent_sdk-2.0.26.dist-info/licenses/LICENSE
trento_agent_sdk-2.0.26.dist-info/METADATA
trento_agent_sdk-2.0.26.dist-info/WHEEL
trento_agent_sdk-2.0.26.dist-info/top_level.txt
trento_agent_sdk-2.0.26.dist-info/RECORD
